MANIFEST.in
setup.py
django_shop_netaxept.egg-info/PKG-INFO
django_shop_netaxept.egg-info/SOURCES.txt
django_shop_netaxept.egg-info/dependency_links.txt
django_shop_netaxept.egg-info/not-zip-safe
django_shop_netaxept.egg-info/requires.txt
django_shop_netaxept.egg-info/top_level.txt
shop_netaxept/__init__.py
shop_netaxept/models.py
shop_netaxept/offsite_netaxept.py
shop_netaxept/templates/shop_netaxept/error.html
shop_netaxept/templates/shop_netaxept/registrationerror.html
shop_netaxept/templates/shop_netaxept/success.html